Workbook

Sheet Categories
A1: Categories | B1: Payment Methods | C1: Paid By | D1: Reimbursement Status
A2: Software & SaaS | B2: Company Card | C2: John Smith | D2: N/A
A3: Hardware & Equipment | B3: Personal Card | C3: Jane Doe | D3: To Submit
A4: Office Supplies | B4: ACH/Bank Transfer | C4: Company | D4: Submitted
A5: Travel - Flights | B5: Cash | D5: Approved
A6: Travel - Lodging | B6: PayPal/Venmo | D6: Paid
A7: Travel - Ground Transport | B7: Other
A8: Meals & Entertainment
A9: Professional Services
A10: Marketing & Ads
A11: Shipping & Postage
A12: Telecommunications
A13: Insurance
A14: Rent & Facilities
A15: Training & Education
A16: Miscellaneous

Sheet Expense Log
A1: ID | B1: Date | C1: Vendor | D1: Amount | E1: Category | F1: Business Purpose | G1: Paid By | H1: Payment Method | I1: Reimbursable? | J1: Reimb. Status | K1: Receipt Link | L1: Receipt Filename | M1: Notes
A2: 1 | B2: 46037 | C2: CloudHost Inc. | D2: 149.99 | E2: Software & SaaS | F2: Monthly cloud hosting | G2: John Smith | H2: Company Card | I2: No | J2: N/A | K2: https://example.com/receipt1 | L2: 2026-01-15_CloudHost_149.99_Hosting.pdf
A3: 2 | B3: 46044 | C3: Office Depot | D3: 47.82 | E3: Office Supplies | F3: Printer paper and toner | G3: Jane Doe | H3: Personal Card | I3: Yes | J3: Submitted | K3: https://example.com/receipt2 | L3: 2026-01-22_OfficeDepot_47.82_Supplies.pdf
A4: 3 | B4: 46056 | C4: Delta Airlines | D4: 389 | E4: Travel - Flights | F4: Client meeting in NYC | G4: John Smith | H4: Company Card | I4: No | J4: N/A | K4: https://example.com/receipt3 | L4: 2026-02-03_Delta_389.00_NYCFlight.pdf
A5: 4 | B5: 46063 | C5: Zoom | D5: 14.99 | E5: Software & SaaS | F5: Monthly video conferencing subscription | G5: Company | H5: ACH/Bank Transfer | I5: No | J5: N/A | L5: 2026-02-10_Zoom_14.99_Subscription.pdf | M5: Auto-renewed
A6: 5 | B6: 46067 | C6: Uber | D6: 32.5 | E6: Travel - Ground Transport | F6: Airport to hotel for client meeting | G6: John Smith | H6: Personal Card | I6: Yes | J6: To Submit | K6: https://example.com/receipt5 | L6: 2026-02-14_Uber_32.50_AirportTransfer.pdf
A7: 6 | B7: 46071 | C7: Marriott | D7: 219 | E7: Travel - Lodging | F7: Hotel for NYC client meeting (1 night) | G7: Jane Doe | H7: Personal Card | I7: Yes | J7: Approved | K7: https://example.com/receipt6 | L7: 2026-02-18_Marriott_219.00_NYCHotel.pdf
A8: 7 | B8: 46082 | C8: Google Ads | D8: 500 | E8: Marketing & Ads | F8: March ad campaign budget | G8: Company | H8: Company Card | I8: No | J8: N/A | M8: Recurring monthly spend
A9: 8 | B9: 46086 | C9: Chipotle | D9: 86.4 | E9: Meals & Entertainment | F9: Team lunch - quarterly planning | G9: John Smith | H9: Personal Card | I9: Yes | J9: To Submit | K9: https://example.com/receipt8 | L9: 2026-03-05_Chipotle_86.40_TeamLunch.pdf | M9: 8 people

Sheet Summary
A1: Expense Summary
A3: Total Expenses | B3: =SUM('Expense Log'!D2:D496) -> 1439.7
A4: Total Reimbursable | B4: =SUMIF('Expense Log'!I2:I496,"Yes",'Expense Log'!D2:D496) -> 385.72
A5: Number of Entries | B5: =COUNTA('Expense Log'!A2:A496) -> 8
A7: Spending by Category
A8: Category | B8: Total | C8: % of Total
A9: Software & SaaS | B9: =SUMIF('Expense Log'!E2:E496,A9,'Expense Log'!D2:D496) -> 164.98 | C9: =IF(B$3=0,0,B9/B$3) -> 0.11459332
A10: Hardware & Equipment | B10: =SUMIF('Expense Log'!E2:E496,A10,'Expense Log'!D2:D496) -> 0 | C10: =IF(B$3=0,0,B10/B$3) -> 0
A11: Office Supplies | B11: =SUMIF('Expense Log'!E2:E496,A11,'Expense Log'!D2:D496) -> 47.82 | C11: =IF(B$3=0,0,B11/B$3) -> 0.033215253
A12: Travel - Flights | B12: =SUMIF('Expense Log'!E2:E496,A12,'Expense Log'!D2:D496) -> 389 | C12: =IF(B$3=0,0,B12/B$3) -> 0.27019518
A13: Travel - Lodging | B13: =SUMIF('Expense Log'!E2:E496,A13,'Expense Log'!D2:D496) -> 219 | C13: =IF(B$3=0,0,B13/B$3) -> 0.15211502
A14: Travel - Ground Transport | B14: =SUMIF('Expense Log'!E2:E496,A14,'Expense Log'!D2:D496) -> 32.5 | C14: =IF(B$3=0,0,B14/B$3) -> 0.022574147
A15: Meals & Entertainment | B15: =SUMIF('Expense Log'!E2:E496,A15,'Expense Log'!D2:D496) -> 86.4 | C15: =IF(B$3=0,0,B15/B$3) -> 0.060012503
A16: Professional Services | B16: =SUMIF('Expense Log'!E2:E496,A16,'Expense Log'!D2:D496) -> 0 | C16: =IF(B$3=0,0,B16/B$3) -> 0
A17: Marketing & Ads | B17: =SUMIF('Expense Log'!E2:E496,A17,'Expense Log'!D2:D496) -> 500 | C17: =IF(B$3=0,0,B17/B$3) -> 0.34729458
A18: Shipping & Postage | B18: =SUMIF('Expense Log'!E2:E496,A18,'Expense Log'!D2:D496) -> 0 | C18: =IF(B$3=0,0,B18/B$3) -> 0
A19: Telecommunications | B19: =SUMIF('Expense Log'!E2:E496,A19,'Expense Log'!D2:D496) -> 0 | C19: =IF(B$3=0,0,B19/B$3) -> 0
A20: Insurance | B20: =SUMIF('Expense Log'!E2:E496,A20,'Expense Log'!D2:D496) -> 0 | C20: =IF(B$3=0,0,B20/B$3) -> 0
A21: Rent & Facilities | B21: =SUMIF('Expense Log'!E2:E496,A21,'Expense Log'!D2:D496) -> 0 | C21: =IF(B$3=0,0,B21/B$3) -> 0
A22: Training & Education | B22: =SUMIF('Expense Log'!E2:E496,A22,'Expense Log'!D2:D496) -> 0 | C22: =IF(B$3=0,0,B22/B$3) -> 0
A23: Miscellaneous | B23: =SUMIF('Expense Log'!E2:E496,A23,'Expense Log'!D2:D496) -> 0 | C23: =IF(B$3=0,0,B23/B$3) -> 0

Sheet Entry Form
B2: New Expense Entry
B3: Fill in the fields below, then copy the row from the "Ready to Copy" section into the Expense Log tab.
B5: Date | C5: 2026-03-01 | G5: Enter date as YYYY-MM-DD
B6: Vendor | C6: Staples | G6: e.g. Amazon, Uber, etc.
B7: Amount | C7: 29.99 | G7: e.g. 49.99
B8: Category | C8: Office Supplies | G8: Select from dropdown
B9: Business Purpose | C9: Pens and notebooks | G9: 1-line description of why
B10: Paid By | C10: John Smith | G10: Select from dropdown
B11: Payment Method | C11: Personal Card | G11: Select from dropdown
B12: Reimbursable? | C12: Yes | G12: Yes or No
B13: Reimb. Status | C13: To Submit | G13: Select from dropdown
B14: Receipt Link | C14: https://example.com/receipt-link | G14: Paste OneDrive share link
B15: Receipt Filename | C15: 2026-03-01_Staples_29.99_OfficeSupplies.pdf | G15: e.g. 2026-02-17_Vendor_Amount_Purpose.pdf
B16: Notes | G16: Optional
B18: Ready to Copy → Paste into Expense Log starting at column B
B19: Date | C19: Vendor | D19: Amount | E19: Category | F19: Business Purpose | G19: Paid By | H19: Payment Method | I19: Reimbursable? | J19: Reimb. Status | K19: Receipt Link | L19: Receipt Filename | M19: Notes
B20: =C5 -> 2026-03-01 | C20: =C6 -> Staples | D20: =C7 -> 29.99 | E20: =C8 -> Office Supplies | F20: =C9 -> Pens and notebooks | G20: =C10 -> John Smith | H20: =C11 -> Personal Card | I20: =C12 -> Yes | J20: =C13 -> To Submit | K20: =C14 -> https://example.com/receipt-link | L20: =C15 -> 2026-03-01_Staples_29.99_OfficeSupplies.pdf | M20: =C16 -> 0
B23: HOW TO USE THIS FORM: 1. Fill in each field above (yellow cells). 2. Select the green "Ready to Copy" row (B20:M20) and copy it. 3. Go to the Expense Log tab, find the next empty row, click column B, and Paste Values (Ctrl+Shift+V). 4. In column A of that row, type the next ID number. 5. Come back here and clear the yellow input cells for your next entry.

Sheet Guidelines
B1: Expense Tracker — Setup & Usage Guidelines
B3: 1. OneDrive Folder Structure
B5: Keep it flat. You only need one folder with yearly subfolders. Don't over-organize — the spreadsheet is your index, not the folder hierarchy.
B7: Recommended structure:
B9: OneDrive/
B10: └── Business Expenses/
B11: ├── 2026/
B12: │ ├── 2026-01/
B13: │ ├── 2026-02/
B14: │ └── ...
B15: ├── 2027/
B16: └── Expense_Tracker.xlsx ← this file
... B94: 4. The Receipt Link column gives them direct access to each receipt without digging through folders.
